audio2book-0.2.0.dist-info/DESCRIPTION.rst
audio2book-0.2.0.dist-info/METADATA
audio2book-0.2.0.dist-info/RECORD
audio2book-0.2.0.dist-info/WHEEL
audio2book-0.2.0.dist-info/entry_points.txt
audio2book-0.2.0.dist-info/metadata.json
audio2book-0.2.0.dist-info/top_level.txt
book/__init__.py
book/__main__.py
book/cli.py
book/convert.py
