Metadata-Version: 2.0
Name: audio2book
Version: 0.2.0
Summary: Converts audiobook completion into page completion
Home-page: https://www.github.com/safuya/books
Author: Robert Hughes
Author-email: roberts.ginger.email@gmail.com
License: UNKNOWN
Platform: UNKNOWN
Classifier: Programming Language :: Python :: 3.6
Classifier: Programming Language :: Python :: 3.7
Classifier: Programming Language :: Python :: 3.8
Classifier: License :: OSI Approved :: GNU General Public License v3 (GPLv3)
Classifier: Intended Audience :: End Users/Desktop
